hdl/top/src/top.sv
// top.sv -- LED blinker example
// Toggles LEDs in a rotating pattern at ~1 Hz given a 100 MHz input clock.

`timescale 1ns / 1ps

module top (
    input  logic       clk,
    input  logic       rst_n,
    output logic [3:0] led
);

    localparam int CLK_FREQ = 100_000_000;
    localparam int HALF_SEC = CLK_FREQ / 2;

    logic [31:0] counter;

    always_ff @(posedge clk or negedge rst_n) begin
        if (!rst_n) begin
            counter <= '0;
            led     <= 4'b0001;
        end else begin
            if (counter == HALF_SEC - 1) begin
                counter <= '0;
                led     <= {led[2:0], led[3]};
            end else begin
                counter <= counter + 1;
            end
        end
    end

endmodule

hdl/top/tb/top_tb.sv
// top_tb.sv -- Verilator-compatible testbench for top module
// Compiled with: verilator --binary -sv --top-module top_tb --timing

`timescale 1ns / 1ps

module top_tb;

    logic       clk;
    logic       rst_n;
    logic [3:0] led;

    top dut (
        .clk   (clk),
        .rst_n (rst_n),
        .led   (led)
    );

    // 100 MHz clock (10 ns period)
    initial clk = 1'b0;
    always #5 clk = ~clk;

    // Waveform dump (active when compiled with --trace)
    initial begin
        $dumpfile("top_tb.vcd");
        $dumpvars(0, top_tb);
    end

    // Stimulus
    initial begin
        $display("=== top_tb: simulation start ===");

        // Assert reset
        rst_n = 1'b0;
        repeat (10) @(posedge clk);

        // Release reset
        rst_n = 1'b1;
        $display("[%0t] Reset released", $time);

        // Verify LED state after reset
        @(posedge clk);
        assert (led == 4'b0001)
            else $error("[%0t] Expected led=0001 after reset, got %b", $time, led);

        // Run for a number of cycles
        repeat (200) @(posedge clk);

        $display("[%0t] LED state: %b", $time, led);
        $display("=== top_tb: simulation end ===");
        $finish;
    end

    // Timeout watchdog
    initial begin
        #10_000_000;
        $display("ERROR: simulation timed out");
        $finish;
    end

endmodule

sim/top/default/top_tb.vcd
$version Generated by VerilatedVcd $end
$timescale 1ps $end
 $scope module top_tb $end
  $var wire 1 # clk $end
  $var wire 1 $ rst_n $end
  $var wire 4 % led [3:0] $end
  $scope module dut $end
   $var wire 1 # clk $end
   $var wire 1 $ rst_n $end
   $var wire 4 % led [3:0] $end
   $var wire 32 ' CLK_FREQ [31:0] $end
   $var wire 32 ( HALF_SEC [31:0] $end
   $var wire 32 & counter [31:0] $end
  $upscope $end
 $upscope $end
$enddefinitions $end


#0
0#
0$
b0000 %
b00000000000000000000000000000000 &
b00000101111101011110000100000000 '
b00000010111110101111000010000000 (
#5000
1#
b0001 %
#10000
0#
#15000
1#
#20000
0#
#25000
1#
#30000
0#
#35000
1#
#40000
0#
#45000
1#
#50000
0#
#55000
1#
#60000
0#
#65000
1#
#70000
0#
#75000
1#
#80000
0#
#85000
1#
#90000
0#
#95000
1#
1$
b00000000000000000000000000000001 &
#100000
0#
#105000
1#
b00000000000000000000000000000010 &
#110000
0#
#115000
1#
b00000000000000000000000000000011 &
#120000
0#
#125000
1#
b00000000000000000000000000000100 &
#130000
0#
#135000
1#
b00000000000000000000000000000101 &
#140000
0#
#145000
1#
b00000000000000000000000000000110 &
#150000
0#
#155000
1#
b00000000000000000000000000000111 &
#160000
0#
#165000
1#
b00000000000000000000000000001000 &
#170000
0#
#175000
1#
b00000000000000000000000000001001 &
#180000
0#
#185000
1#
b00000000000000000000000000001010 &
#190000
0#
#195000
1#
b00000000000000000000000000001011 &
#200000
0#
#205000
1#
b00000000000000000000000000001100 &
#210000
0#
#215000
1#
b00000000000000000000000000001101 &
#220000
0#
#225000
1#
b00000000000000000000000000001110 &
#230000
0#
#235000
1#
b00000000000000000000000000001111 &
#240000
0#
#245000
1#
b00000000000000000000000000010000 &
#250000
0#
#255000
1#
b00000000000000000000000000010001 &
#260000
0#
#265000
1#
b00000000000000000000000000010010 &
#270000
0#
#275000
1#
b00000000000000000000000000010011 &
#280000
0#
#285000
1#
b00000000000000000000000000010100 &
#290000
0#
#295000
1#
b00000000000000000000000000010101 &
#300000
0#
#305000
1#
b00000000000000000000000000010110 &
#310000
0#
#315000
1#
b00000000000000000000000000010111 &
#320000
0#
#325000
1#
b00000000000000000000000000011000 &
#330000
0#
#335000
1#
b00000000000000000000000000011001 &
#340000
0#
#345000
1#
b00000000000000000000000000011010 &
#350000
0#
#355000
1#
b00000000000000000000000000011011 &
#360000
0#
#365000
1#
b00000000000000000000000000011100 &
#370000
0#
#375000
1#
b00000000000000000000000000011101 &
#380000
0#
#385000
1#
b00000000000000000000000000011110 &
#390000
0#
#395000
1#
b00000000000000000000000000011111 &
#400000
0#
#405000
1#
b00000000000000000000000000100000 &
#410000
0#
#415000
1#
b00000000000000000000000000100001 &
#420000
0#
#425000
1#
b00000000000000000000000000100010 &
#430000
0#
#435000
1#
b00000000000000000000000000100011 &
#440000
0#
#445000
1#
b00000000000000000000000000100100 &
#450000
0#
#455000
1#
b00000000000000000000000000100101 &
#460000
0#
#465000
1#
b00000000000000000000000000100110 &
#470000
0#
#475000
1#
b00000000000000000000000000100111 &
#480000
0#
#485000
1#
b00000000000000000000000000101000 &
#490000
0#
#495000
1#
b00000000000000000000000000101001 &
#500000
0#
#505000
1#
b00000000000000000000000000101010 &
#510000
0#
#515000
1#
b00000000000000000000000000101011 &
#520000
0#
#525000
1#
b00000000000000000000000000101100 &
#530000
0#
#535000
1#
b00000000000000000000000000101101 &
#540000
0#
#545000
1#
b00000000000000000000000000101110 &
#550000
0#
#555000
1#
b00000000000000000000000000101111 &
#560000
0#
#565000
1#
b00000000000000000000000000110000 &
#570000
0#
#575000
1#
b00000000000000000000000000110001 &
#580000
0#
#585000
1#
b00000000000000000000000000110010 &
#590000
0#
#595000
1#
b00000000000000000000000000110011 &
#600000
0#
#605000
1#
b00000000000000000000000000110100 &
#610000
0#
#615000
1#
b00000000000000000000000000110101 &
#620000
0#
#625000
1#
b00000000000000000000000000110110 &
#630000
0#
#635000
1#
b00000000000000000000000000110111 &
#640000
0#
#645000
1#
b00000000000000000000000000111000 &
#650000
0#
#655000
1#
b00000000000000000000000000111001 &
#660000
0#
#665000
1#
b00000000000000000000000000111010 &
#670000
0#
#675000
1#
b00000000000000000000000000111011 &
#680000
0#
#685000
1#
b00000000000000000000000000111100 &
#690000
0#
#695000
1#
b00000000000000000000000000111101 &
#700000
0#
#705000
1#
b00000000000000000000000000111110 &
#710000
0#
#715000
1#
b00000000000000000000000000111111 &
#720000
0#
#725000
1#
b00000000000000000000000001000000 &
#730000
0#
#735000
1#
b00000000000000000000000001000001 &
#740000
0#
#745000
1#
b00000000000000000000000001000010 &
#750000
0#
#755000
1#
b00000000000000000000000001000011 &
#760000
0#
#765000
1#
b00000000000000000000000001000100 &
#770000
0#
#775000
1#
b00000000000000000000000001000101 &
#780000
0#
#785000
1#
b00000000000000000000000001000110 &
#790000
0#
#795000
1#
b00000000000000000000000001000111 &
#800000
0#
#805000
1#
b00000000000000000000000001001000 &
#810000
0#
#815000
1#
b00000000000000000000000001001001 &
#820000
0#
#825000
1#
b00000000000000000000000001001010 &
#830000
0#
#835000
1#
b00000000000000000000000001001011 &
#840000
0#
#845000
1#
b00000000000000000000000001001100 &
#850000
0#
#855000
1#
b00000000000000000000000001001101 &
#860000
0#
#865000
1#
b00000000000000000000000001001110 &
#870000
0#
#875000
1#
b00000000000000000000000001001111 &
#880000
0#
#885000
1#
b00000000000000000000000001010000 &
#890000
0#
#895000
1#
b00000000000000000000000001010001 &
#900000
0#
#905000
1#
b00000000000000000000000001010010 &
#910000
0#
#915000
1#
b00000000000000000000000001010011 &
#920000
0#
#925000
1#
b00000000000000000000000001010100 &
#930000
0#
#935000
1#
b00000000000000000000000001010101 &
#940000
0#
#945000
1#
b00000000000000000000000001010110 &
#950000
0#
#955000
1#
b00000000000000000000000001010111 &
#960000
0#
#965000
1#
b00000000000000000000000001011000 &
#970000
0#
#975000
1#
b00000000000000000000000001011001 &
#980000
0#
#985000
1#
b00000000000000000000000001011010 &
#990000
0#
#995000
1#
b00000000000000000000000001011011 &
#1000000
0#
#1005000
1#
b00000000000000000000000001011100 &
#1010000
0#
#1015000
1#
b00000000000000000000000001011101 &
#1020000
0#
#1025000
1#
b00000000000000000000000001011110 &
#1030000
0#
#1035000
1#
b00000000000000000000000001011111 &
#1040000
0#
#1045000
1#
b00000000000000000000000001100000 &
#1050000
0#
#1055000
1#
b00000000000000000000000001100001 &
#1060000
0#
#1065000
1#
b00000000000000000000000001100010 &
#1070000
0#
#1075000
1#
b00000000000000000000000001100011 &
#1080000
0#
#1085000
1#
b00000000000000000000000001100100 &
#1090000
0#
#1095000
1#
b00000000000000000000000001100101 &
#1100000
0#
#1105000
1#
b00000000000000000000000001100110 &
#1110000
0#
#1115000
1#
b00000000000000000000000001100111 &
#1120000
0#
#1125000
1#
b00000000000000000000000001101000 &
#1130000
0#
#1135000
1#
b00000000000000000000000001101001 &
#1140000
0#
#1145000
1#
b00000000000000000000000001101010 &
#1150000
0#
#1155000
1#
b00000000000000000000000001101011 &
#1160000
0#
#1165000
1#
b00000000000000000000000001101100 &
#1170000
0#
#1175000
1#
b00000000000000000000000001101101 &
#1180000
0#
#1185000
1#
b00000000000000000000000001101110 &
#1190000
0#
#1195000
1#
b00000000000000000000000001101111 &
#1200000
0#
#1205000
1#
b00000000000000000000000001110000 &
#1210000
0#
#1215000
1#
b00000000000000000000000001110001 &
#1220000
0#
#1225000
1#
b00000000000000000000000001110010 &
#1230000
0#
#1235000
1#
b00000000000000000000000001110011 &
#1240000
0#
#1245000
1#
b00000000000000000000000001110100 &
#1250000
0#
#1255000
1#
b00000000000000000000000001110101 &
#1260000
0#
#1265000
1#
b00000000000000000000000001110110 &
#1270000
0#
#1275000
1#
b00000000000000000000000001110111 &
#1280000
0#
#1285000
1#
b00000000000000000000000001111000 &
#1290000
0#
#1295000
1#
b00000000000000000000000001111001 &
#1300000
0#
#1305000
1#
b00000000000000000000000001111010 &
#1310000
0#
#1315000
1#
b00000000000000000000000001111011 &
#1320000
0#
#1325000
1#
b00000000000000000000000001111100 &
#1330000
0#
#1335000
1#
b00000000000000000000000001111101 &
#1340000
0#
#1345000
1#
b00000000000000000000000001111110 &
#1350000
0#
#1355000
1#
b00000000000000000000000001111111 &
#1360000
0#
#1365000
1#
b00000000000000000000000010000000 &
#1370000
0#
#1375000
1#
b00000000000000000000000010000001 &
#1380000
0#
#1385000
1#
b00000000000000000000000010000010 &
#1390000
0#
#1395000
1#
b00000000000000000000000010000011 &
#1400000
0#
#1405000
1#
b00000000000000000000000010000100 &
#1410000
0#
#1415000
1#
b00000000000000000000000010000101 &
#1420000
0#
#1425000
1#
b00000000000000000000000010000110 &
#1430000
0#
#1435000
1#
b00000000000000000000000010000111 &
#1440000
0#
#1445000
1#
b00000000000000000000000010001000 &
#1450000
0#
#1455000
1#
b00000000000000000000000010001001 &
#1460000
0#
#1465000
1#
b00000000000000000000000010001010 &
#1470000
0#
#1475000
1#
b00000000000000000000000010001011 &
#1480000
0#
#1485000
1#
b00000000000000000000000010001100 &
#1490000
0#
#1495000
1#
b00000000000000000000000010001101 &
#1500000
0#
#1505000
1#
b00000000000000000000000010001110 &
#1510000
0#
#1515000
1#
b00000000000000000000000010001111 &
#1520000
0#
#1525000
1#
b00000000000000000000000010010000 &
#1530000
0#
#1535000
1#
b00000000000000000000000010010001 &
#1540000
0#
#1545000
1#
b00000000000000000000000010010010 &
#1550000
0#
#1555000
1#
b00000000000000000000000010010011 &
#1560000
0#
#1565000
1#
b00000000000000000000000010010100 &
#1570000
0#
#1575000
1#
b00000000000000000000000010010101 &
#1580000
0#
#1585000
1#
b00000000000000000000000010010110 &
#1590000
0#
#1595000
1#
b00000000000000000000000010010111 &
#1600000
0#
#1605000
1#
b00000000000000000000000010011000 &
#1610000
0#
#1615000
1#
b00000000000000000000000010011001 &
#1620000
0#
#1625000
1#
b00000000000000000000000010011010 &
#1630000
0#
#1635000
1#
b00000000000000000000000010011011 &
#1640000
0#
#1645000
1#
b00000000000000000000000010011100 &
#1650000
0#
#1655000
1#
b00000000000000000000000010011101 &
#1660000
0#
#1665000
1#
b00000000000000000000000010011110 &
#1670000
0#
#1675000
1#
b00000000000000000000000010011111 &
#1680000
0#
#1685000
1#
b00000000000000000000000010100000 &
#1690000
0#
#1695000
1#
b00000000000000000000000010100001 &
#1700000
0#
#1705000
1#
b00000000000000000000000010100010 &
#1710000
0#
#1715000
1#
b00000000000000000000000010100011 &
#1720000
0#
#1725000
1#
b00000000000000000000000010100100 &
#1730000
0#
#1735000
1#
b00000000000000000000000010100101 &
#1740000
0#
#1745000
1#
b00000000000000000000000010100110 &
#1750000
0#
#1755000
1#
b00000000000000000000000010100111 &
#1760000
0#
#1765000
1#
b00000000000000000000000010101000 &
#1770000
0#
#1775000
1#
b00000000000000000000000010101001 &
#1780000
0#
#1785000
1#
b00000000000000000000000010101010 &
#1790000
0#
#1795000
1#
b00000000000000000000000010101011 &
#1800000
0#
#1805000
1#
b00000000000000000000000010101100 &
#1810000
0#
#1815000
1#
b00000000000000000000000010101101 &
#1820000
0#
#1825000
1#
b00000000000000000000000010101110 &
#1830000
0#
#1835000
1#
b00000000000000000000000010101111 &
#1840000
0#
#1845000
1#
b00000000000000000000000010110000 &
#1850000
0#
#1855000
1#
b00000000000000000000000010110001 &
#1860000
0#
#1865000
1#
b00000000000000000000000010110010 &
#1870000
0#
#1875000
1#
b00000000000000000000000010110011 &
#1880000
0#
#1885000
1#
b00000000000000000000000010110100 &
#1890000
0#
#1895000
1#
b00000000000000000000000010110101 &
#1900000
0#
#1905000
1#
b00000000000000000000000010110110 &
#1910000
0#
#1915000
1#
b00000000000000000000000010110111 &
#1920000
0#
#1925000
1#
b00000000000000000000000010111000 &
#1930000
0#
#1935000
1#
b00000000000000000000000010111001 &
#1940000
0#
#1945000
1#
b00000000000000000000000010111010 &
#1950000
0#
#1955000
1#
b00000000000000000000000010111011 &
#1960000
0#
#1965000
1#
b00000000000000000000000010111100 &
#1970000
0#
#1975000
1#
b00000000000000000000000010111101 &
#1980000
0#
#1985000
1#
b00000000000000000000000010111110 &
#1990000
0#
#1995000
1#
b00000000000000000000000010111111 &
#2000000
0#
#2005000
1#
b00000000000000000000000011000000 &
#2010000
0#
#2015000
1#
b00000000000000000000000011000001 &
#2020000
0#
#2025000
1#
b00000000000000000000000011000010 &
#2030000
0#
#2035000
1#
b00000000000000000000000011000011 &
#2040000
0#
#2045000
1#
b00000000000000000000000011000100 &
#2050000
0#
#2055000
1#
b00000000000000000000000011000101 &
#2060000
0#
#2065000
1#
b00000000000000000000000011000110 &
#2070000
0#
#2075000
1#
b00000000000000000000000011000111 &
#2080000
0#
#2085000
1#
b00000000000000000000000011001000 &
#2090000
0#
#2095000
1#
b00000000000000000000000011001001 &
#2100000
0#
#2105000
1#
b00000000000000000000000011001010 &
